KcangNacos/__init__.py
KcangNacos/nacos.py
KcangNacos-1.7.dist-info/LICENSE.txt
KcangNacos-1.7.dist-info/METADATA
KcangNacos-1.7.dist-info/WHEEL
KcangNacos-1.7.dist-info/top_level.txt
KcangNacos-1.7.dist-info/RECORD
